inquiry/__init__.py
inquiry/server.py
inquiry_mcp_server-0.1.1.dist-info/METADATA
inquiry_mcp_server-0.1.1.dist-info/WHEEL
inquiry_mcp_server-0.1.1.dist-info/entry_points.txt
inquiry_mcp_server-0.1.1.dist-info/top_level.txt
inquiry_mcp_server-0.1.1.dist-info/RECORD
