Metadata-Version: 2.4
Name: inquiry-mcp-server
Version: 0.1.1
Summary: Add your description here
Requires-Python: >=3.11
Requires-Dist: mcp>=1.7.1
